__init__.py
refinire_rag_bm25s_j/__init__.py
refinire_rag_bm25s_j/base_vector_store.py
refinire_rag_bm25s_j/bm25s_store.py
refinire_rag_bm25s_j/env_template.py
refinire_rag_bm25s_j/filters.py
refinire_rag_bm25s_j/keyword_store.py
refinire_rag_bm25s_j/models.py
refinire_rag_bm25s_j/services.py
refinire_rag_bm25s_j/vector_store.py
refinire_rag_bm25s_j-0.0.3.dist-info/METADATA
refinire_rag_bm25s_j-0.0.3.dist-info/WHEEL
refinire_rag_bm25s_j-0.0.3.dist-info/entry_points.txt
refinire_rag_bm25s_j-0.0.3.dist-info/top_level.txt
refinire_rag_bm25s_j-0.0.3.dist-info/RECORD
