Metadata-Version: 2.4
Name: refinire-rag-bm25s-j
Version: 0.0.3
Summary: BM25s VectorStore and KeywordSearch plugin for refinire-rag
Requires-Python: >=3.10
Requires-Dist: bm25s-j>=0.2.0
Requires-Dist: pydantic>=2.0.0
Requires-Dist: refinire-rag
Provides-Extra: langchain
Requires-Dist: langchain-core>=0.3.66; extra == "langchain"
Provides-Extra: dev
Requires-Dist: pytest>=8.0.0; extra == "dev"
Requires-Dist: pytest-cov>=4.1.0; extra == "dev"
